LICENSE
MANIFEST.in
README.md
setup.cfg
setup.py
./LICENSE
./README.md
./__init__.py
./_info.py
./chord_diagram.py
./example.py
./gradient.py
./utilities.py
mpl_chord_diagram.egg-info/PKG-INFO
mpl_chord_diagram.egg-info/SOURCES.txt
mpl_chord_diagram.egg-info/dependency_links.txt
mpl_chord_diagram.egg-info/requires.txt
mpl_chord_diagram.egg-info/top_level.txt