Metadata-Version: 2.1
Name: mpl_chord_diagram
Version: 0.4.1
Summary: Python module to plot chord diagrams with matplotlib.
Home-page: https://codeberg.org/tfardet/mpl_chord_diagram
Author: Tanguy Fardet
Author-email: tanguyfardet@protonmail.com
License: MIT
Keywords: chord diagram matplotlib plotting
Classifier: Development Status :: 5 - Production/Stable
Classifier: Intended Audience :: Science/Research
Classifier: License :: OSI Approved :: MIT License
Classifier: Natural Language :: English
Classifier: Programming Language :: Python :: 3
Classifier: Operating System :: OS Independent
Classifier: Topic :: Scientific/Engineering :: Visualization
Classifier: Framework :: Matplotlib
License-File: LICENSE
